gecco/__init__.py
gecco/__main__.py
gecco/_base.py
gecco/_meta.py
gecco/model.py
gecco/orf.py
gecco/py.typed
gecco/refine.py
gecco/cli/__init__.py
gecco/cli/_utils.py
gecco/cli/commands/__init__.py
gecco/cli/commands/_base.py
gecco/cli/commands/_main.py
gecco/cli/commands/_mixins.py
gecco/cli/commands/annotate.py
gecco/cli/commands/convert.py
gecco/cli/commands/cv.py
gecco/cli/commands/help.py
gecco/cli/commands/predict.py
gecco/cli/commands/run.py
gecco/cli/commands/train.py
gecco/crf/__init__.py
gecco/crf/cv.py
gecco/crf/features.py
gecco/crf/model.pkl
gecco/crf/model.pkl.md5
gecco/crf/select.py
gecco/hmmer/Pfam.h3m
gecco/hmmer/Pfam.ini
gecco/hmmer/__init__.py
gecco/interpro/__init__.py
gecco/interpro/interpro.json
gecco/types/__init__.py
gecco/types/compositions.npz
gecco/types/domains.tsv
gecco/types/types.tsv
gecco_tool-0.9.10.dist-info/LICENSE
gecco_tool-0.9.10.dist-info/METADATA
gecco_tool-0.9.10.dist-info/WHEEL
gecco_tool-0.9.10.dist-info/entry_points.txt
gecco_tool-0.9.10.dist-info/top_level.txt
gecco_tool-0.9.10.dist-info/RECORD
