Metadata-Version: 2.1
Name: gecco-tool
Version: 0.9.10
Summary: Gene cluster prediction with Conditional random fields.
Home-page: https://gecco.embl.de
Author: Martin Larralde
Author-email: martin.larralde@embl.de
License: GPLv3
Project-URL: Repository, https://github.com/zellerlab/GECCO
Project-URL: Bug Tracker, https://github.com/zellerlab/GECCO/issues
Project-URL: Changelog, https://github.com/zellerlab/GECCO/blob/master/CHANGELOG.md
Project-URL: Coverage, https://codecov.io/gh/zellerlab/GECCO/
Project-URL: Builds, https://git.embl.de/grp-zeller/GECCO/-/pipelines
Project-URL: Preprint, https://www.biorxiv.org/content/10.1101/2021.05.03.442509v1
Platform: x86
Platform: x86_64
Platform: powerpc
Platform: ppc64
Classifier: Development Status :: 3 - Alpha
Classifier: Intended Audience :: Science/Research
Classifier: License :: OSI Approved :: GNU General Public License v3 (GPLv3)
Classifier: Operating System :: POSIX
Classifier: Programming Language :: Python :: 3 :: Only
Classifier: Programming Language :: Python :: 3.7
Classifier: Programming Language :: Python :: 3.8
Classifier: Programming Language :: Python :: 3.9
Classifier: Programming Language :: Python :: 3.10
Classifier: Programming Language :: Python :: 3.11
Classifier: Topic :: Scientific/Engineering :: Bio-Informatics
Classifier: Topic :: Scientific/Engineering :: Medical Science Apps.
Classifier: Typing :: Typed
Requires-Python: >=3.7
License-File: LICENSE
Requires-Dist: biopython ~=1.73
Requires-Dist: docopt ~=0.6.2
Requires-Dist: numpy ~=1.16
Requires-Dist: polars <0.21,>=0.16
Requires-Dist: psutil ~=5.8
Requires-Dist: pyhmmer ~=0.10.0
Requires-Dist: pyrodigal ~=3.0
Requires-Dist: rich >=12.4.0
Requires-Dist: scikit-learn ~=1.0
Requires-Dist: scipy ~=1.4
Requires-Dist: sklearn-crfsuite ~=0.3.6
Requires-Dist: importlib-metadata >=4.0 ; python_version < "3.10"
Requires-Dist: importlib-resources >=1.0 ; python_version < "3.9"
Provides-Extra: train
Requires-Dist: fisher ~=0.1.10 ; extra == 'train'
Requires-Dist: statsmodels <0.15,>=0.13 ; extra == 'train'
